Metadata-Version: 2.1
Name: scrapy-crawlbase-middleware
Version: 1.0.0
Summary: Scrapy Crawlbase Proxy Middleware: Crawlbase interfacing middleware for Scrapy
Home-page: https://github.com/crawlbase-source/scrapy-crawlbase-middleware
Author: Crawlbase
Author-email: info@crawlbase.com
License: Apache-2.0
Keywords: scrapy middleware scraping scraper crawler crawling crawlbase api
Platform: UNKNOWN
Classifier: Programming Language :: Python :: 2
Classifier: Programming Language :: Python :: 2.7
Classifier: Programming Language :: Python :: 3
Classifier: Programming Language :: Python :: 3.5
Classifier: Development Status :: 5 - Production/Stable
Classifier: Intended Audience :: Developers
Classifier: License :: OSI Approved :: Apache Software License
Classifier: Operating System :: OS Independent
Classifier: Topic :: Utilities
